pyclimenu/__init__.py
py_climenu-0.1.0.dist-info/LICENSE
py_climenu-0.1.0.dist-info/METADATA
py_climenu-0.1.0.dist-info/WHEEL
py_climenu-0.1.0.dist-info/top_level.txt
py_climenu-0.1.0.dist-info/RECORD
