Metadata-Version: 2.1
Name: py-climenu
Version: 0.1.0
Summary: Python menu for CLI
Home-page: https://github.com/baely/PyCLIMenu
Author: baely
Author-email: contact@baely.dev
License: UNKNOWN
Platform: UNKNOWN
Classifier: Programming Language :: Python :: 3
Classifier: License :: OSI Approved :: MIT License
Classifier: Operating System :: OS Independent
Requires-Python: >=3.8
